djcheckup/__init__.py
djcheckup/api.py
djcheckup/check_defs.py
djcheckup/checks.py
djcheckup/cli.py
djcheckup/outputs.py
djcheckup-0.5.0.dist-info/WHEEL
djcheckup-0.5.0.dist-info/entry_points.txt
djcheckup-0.5.0.dist-info/METADATA
djcheckup-0.5.0.dist-info/RECORD
