Metadata-Version: 2.3
Name: djcheckup
Version: 0.5.0
Summary: DJ Checkup is a security scanner for Django sites.
Author: Stuart Maxwell
Author-email: Stuart Maxwell <stuart@amanzi.nz>
License: BSD 3-Clause License
Classifier: Programming Language :: Python
Classifier: Programming Language :: Python :: 3.10
Classifier: Programming Language :: Python :: 3.11
Classifier: Programming Language :: Python :: 3.12
Classifier: Programming Language :: Python :: 3.13
Classifier: Programming Language :: Python :: 3.14
Requires-Dist: httpx>=0.28.1
Requires-Dist: rich>=14.1.0
Requires-Dist: typer>=0.17.4
Requires-Python: >=3.10
Project-URL: Homepage, https://github.com/stuartmaxwell/djcheckup
Project-URL: Repository, https://github.com/stuartmaxwell/djcheckup
